[
    {
        "image": "APERAM1_0030_1",
        "label": "Acier",
        "coordinates": {
            "x1": 0.0035563365549558324,
            "y1": 0.007506007506007696,
            "x2": 0.09309233923266806,
            "y2": 0.11280611280611304
        }
    },
    {
        "image": "APERAM1_0030_1",
        "label": "Acier",
        "coordinates": {
            "x1": 0.6336554955859588,
            "y1": 0.014256014256014438,
            "x2": 0.7784193129994561,
            "y2": 0.1168561168561171
        }
    }
]