[
    {
        "image": "APERAM1_0010_1",
        "label": "Acier",
        "coordinates": {
            "x1": 0.0035563365549558658,
            "y1": 0.0034560034560035184,
            "x2": 0.07803020794109033,
            "y2": 0.0993060993060994
        }
    },
    {
        "image": "APERAM1_0010_1",
        "label": "Acier",
        "coordinates": {
            "x1": 0.7298857788377058,
            "y1": 0.00750600750600759,
            "x2": 0.8386678381657673,
            "y2": 0.09795609795609798
        }
    }
]